README.txt
setup.py
Chandler_DependencyPlugin.egg-info/PKG-INFO
Chandler_DependencyPlugin.egg-info/SOURCES.txt
Chandler_DependencyPlugin.egg-info/dependency_links.txt
Chandler_DependencyPlugin.egg-info/entry_points.txt
Chandler_DependencyPlugin.egg-info/top_level.txt
dependency/Dependency.py
dependency/__init__.py
dependency/ui.py
