Metadata-Version: 1.0
Name: Chandler-DependencyPlugin
Version: 0.1
Summary: Support Dependencies between items in Chandler
Home-page: UNKNOWN
Author: Jeffrey Harris
Author-email: UNKNOWN
License: UNKNOWN
Platform: UNKNOWN
Classifier: Development Status :: 3 - Alpha
Classifier: Environment :: Plugins
Classifier: Framework :: Chandler
Classifier: License :: OSI Approved :: Apache Software License
Classifier: Operating System :: OS Independent
Classifier: Programming Language :: Python
Classifier: Topic :: Office/Business :: Groupware
